mongoguard/__init__.py
mongoguard/log_manager.py
mongoguard/mongoguard.py
mongoguard-0.1.6.dist-info/licenses/LICENSE
mongoguard-0.1.6.dist-info/METADATA
mongoguard-0.1.6.dist-info/WHEEL
mongoguard-0.1.6.dist-info/top_level.txt
mongoguard-0.1.6.dist-info/RECORD
